cropengine/__init__.py
cropengine/agromanagement.py
cropengine/assimilation.py
cropengine/conversions.py
cropengine/crop.py
cropengine/cropengine.py
cropengine/models.py
cropengine/optimizer.py
cropengine/output.py
cropengine/sensitivity.py
cropengine/site.py
cropengine/soil.py
cropengine/weather.py
cropengine/configs/__init__.py
cropengine/configs/agromanagement.yaml
cropengine/configs/crop_params.yaml
cropengine/configs/meteo.yaml
cropengine/configs/models.yaml
cropengine/configs/output.yaml
cropengine/configs/site_params.yaml
cropengine/configs/soil.yaml
cropengine/configs/soil_params.yaml
cropengine/configs/wofost_crop_params/WOFOSTCropParametersProvider.pkl
cropengine/configs/wofost_crop_params/barley.yaml
cropengine/configs/wofost_crop_params/cassava.yaml
cropengine/configs/wofost_crop_params/chickpea.yaml
cropengine/configs/wofost_crop_params/cotton.yaml
cropengine/configs/wofost_crop_params/cowpea.yaml
cropengine/configs/wofost_crop_params/crops.yaml
cropengine/configs/wofost_crop_params/fababean.yaml
cropengine/configs/wofost_crop_params/groundnut.yaml
cropengine/configs/wofost_crop_params/maize.yaml
cropengine/configs/wofost_crop_params/millet.yaml
cropengine/configs/wofost_crop_params/mungbean.yaml
cropengine/configs/wofost_crop_params/pigeonpea.yaml
cropengine/configs/wofost_crop_params/potato.yaml
cropengine/configs/wofost_crop_params/rapeseed.yaml
cropengine/configs/wofost_crop_params/rice.yaml
cropengine/configs/wofost_crop_params/seed_onion.yaml
cropengine/configs/wofost_crop_params/sorghum.yaml
cropengine/configs/wofost_crop_params/soybean.yaml
cropengine/configs/wofost_crop_params/sugarbeet.yaml
cropengine/configs/wofost_crop_params/sugarcane.yaml
cropengine/configs/wofost_crop_params/sunflower.yaml
cropengine/configs/wofost_crop_params/sweetpotato.yaml
cropengine/configs/wofost_crop_params/tobacco.yaml
cropengine/configs/wofost_crop_params/wheat.yaml
cropengine-1.1.0.dist-info/licenses/LICENSE
cropengine-1.1.0.dist-info/METADATA
cropengine-1.1.0.dist-info/WHEEL
cropengine-1.1.0.dist-info/entry_points.txt
cropengine-1.1.0.dist-info/top_level.txt
cropengine-1.1.0.dist-info/RECORD
