Metadata-Version: 2.4
Name: cropengine
Version: 1.1.0
Summary: cropengine is a Python package that streamlines running process-based crop models by automating data preparation, simulation workflows, and result analysis.
Author-email: Krishnagopal Halder <geonextgis@gmail.com>
License: MIT License
Project-URL: Homepage, https://github.com/geonextgis/cropengine
Keywords: cropengine
Classifier: Intended Audience :: Developers
Classifier: License :: OSI Approved :: MIT License
Classifier: Natural Language :: English
Classifier: Programming Language :: Python :: 3.8
Classifier: Programming Language :: Python :: 3.9
Classifier: Programming Language :: Python :: 3.10
Classifier: Programming Language :: Python :: 3.11
Classifier: Programming Language :: Python :: 3.12
Requires-Python: >=3.8
License-File: LICENSE
Requires-Dist: cma
Requires-Dist: cmaes
Requires-Dist: earthengine-api>=1.7
Requires-Dist: geeagri>1.0.0
Requires-Dist: geemap
Requires-Dist: importlib
Requires-Dist: joblib
Requires-Dist: matplotlib
Requires-Dist: numpy
Requires-Dist: optuna
Requires-Dist: pandas
Requires-Dist: pcse
Requires-Dist: pedon
Requires-Dist: PyYAML
Requires-Dist: SALib
Requires-Dist: scipy
Requires-Dist: seaborn
Provides-Extra: all
Requires-Dist: cropengine[extra]; extra == "all"
Provides-Extra: extra
Requires-Dist: pandas; extra == "extra"
Dynamic: license-file
